{
  "country": {
    "code": "SRB",
    "group": "sr",
    "name": "Serbia"
  },
  "traffic": [
    {
      "date": "2020-04-26",
      "views": 1.8923964893737323e-05
    },
    {
      "date": "2021-02-05",
      "views": 2.257176459050538e-05
    },
    {
      "date": "2020-04-23",
      "views": 1.5103444434899907e-05
    },
    {
      "date": "2020-10-03",
      "views": 1.2369587822140789e-05
    },
    {
      "date": "2019-10-31",
      "views": 1.3335330669526947e-05
    },
    {
      "date": "2021-01-27",
      "views": 4.062808002227021e-05
    },
    {
      "date": "2020-03-07",
      "views": 1.17542253346861e-05
    },
    {
      "date": "2020-03-05",
      "views": 1.6004123545211372e-05
    },
    {
      "date": "2020-03-06",
      "views": 1.3161850219197453e-05
    },
    {
      "date": "2020-04-24",
      "views": 1.3705013293862894e-05
    },
    {
      "date": "2020-04-27",
      "views": 1.1944687410245175e-05
    },
    {
      "date": "2021-02-15",
      "views": 1.0440023803254271e-05
    },
    {
      "date": "2019-10-24",
      "views": 2.3180085154360822e-05
    },
    {
      "date": "2019-12-11",
      "views": 3.084674309804123e-05
    },
    {
      "date": "2021-02-17",
      "views": 7.82120180586949e-06
    },
    {
      "date": "2021-02-16",
      "views": 1.6143671501397324e-05
    },
    {
      "date": "2020-04-21",
      "views": 2.1788203461284135e-05
    },
    {
      "date": "2020-04-20",
      "views": 2.3830409190821435e-05
    },
    {
      "date": "2021-03-15",
      "views": 2.360646731362694e-05
    },
    {
      "date": "2019-11-02",
      "views": 1.9867900536874822e-05
    },
    {
      "date": "2021-03-01",
      "views": 1.895621260704792e-05
    },
    {
      "date": "2021-02-18",
      "views": 1.546856208114034e-05
    },
    {
      "date": "2020-04-12",
      "views": 2.5491421247514586e-05
    },
    {
      "date": "2020-04-05",
      "views": 2.6968447502692447e-05
    },
    {
      "date": "2020-04-02",
      "views": 3.6338883116750175e-05
    },
    {
      "date": "2021-02-28",
      "views": 1.6062990286271692e-05
    },
    {
      "date": "2021-03-07",
      "views": 1.5428682074262876e-05
    },
    {
      "date": "2020-04-29",
      "views": 1.6699622327603798e-05
    },
    {
      "date": "2021-03-09",
      "views": 1.8406662645518826e-05
    },
    {
      "date": "2021-02-19",
      "views": 1.57581835112098e-05
    },
    {
      "date": "2021-03-02",
      "views": 1.7751281820060225e-05
    },
    {
      "date": "2020-05-03",
      "views": 2.696995108403523e-05
    },
    {
      "date": "2020-04-25",
      "views": 2.398378191420875e-05
    },
    {
      "date": "2021-02-14",
      "views": 2.1474001491467013e-05
    },
    {
      "date": "2021-03-03",
      "views": 2.8944601597116178e-05
    },
    {
      "date": "2020-04-22",
      "views": 1.884564163127874e-05
    },
    {
      "date": "2020-04-13",
      "views": 2.4819753753410552e-05
    },
    {
      "date": "2021-02-21",
      "views": 2.8029223268179405e-05
    },
    {
      "date": "2020-04-14",
      "views": 1.582633759754217e-05
    },
    {
      "date": "2020-04-28",
      "views": 2.4310721967665636e-05
    },
    {
      "date": "2020-04-03",
      "views": 2.5518160424168533e-05
    },
    {
      "date": "2020-05-02",
      "views": 2.9158693923781766e-05
    },
    {
      "date": "2020-04-07",
      "views": 2.0957234462894195e-05
    },
    {
      "date": "2020-04-04",
      "views": 2.401674161620987e-05
    },
    {
      "date": "2021-02-27",
      "views": 2.031253173833084e-05
    },
    {
      "date": "2021-03-17",
      "views": 1.8267175711963175e-05
    },
    {
      "date": "2021-03-04",
      "views": 2.6182662951373243e-05
    },
    {
      "date": "2021-03-11",
      "views": 2.5069236356242205e-05
    },
    {
      "date": "2020-04-06",
      "views": 1.9390795081848008e-05
    },
    {
      "date": "2020-05-06",
      "views": 2.3191829235733067e-05
    },
    {
      "date": "2020-05-21",
      "views": 1.2803324474652162e-05
    },
    {
      "date": "2021-03-10",
      "views": 1.5723573853983746e-05
    },
    {
      "date": "2021-03-18",
      "views": 2.083781098200268e-05
    },
    {
      "date": "2020-04-15",
      "views": 2.0276298358971586e-05
    },
    {
      "date": "2020-05-01",
      "views": 2.6726603791788023e-05
    },
    {
      "date": "2020-04-10",
      "views": 1.9574726825511495e-05
    },
    {
      "date": "2020-04-01",
      "views": 2.1648255968978577e-05
    },
    {
      "date": "2020-01-16",
      "views": 3.110912256719799e-05
    },
    {
      "date": "2021-03-16",
      "views": 4.255478611138811e-05
    },
    {
      "date": "2021-03-06",
      "views": 1.4748046968191933e-05
    },
    {
      "date": "2020-02-02",
      "views": 1.854625203429202e-05
    },
    {
      "date": "2020-04-11",
      "views": 1.756246332321776e-05
    },
    {
      "date": "2020-03-11",
      "views": 1.4960946176269867e-05
    },
    {
      "date": "2020-04-19",
      "views": 2.7227476249400815e-05
    },
    {
      "date": "2021-02-20",
      "views": 2.2087564244346345e-05
    },
    {
      "date": "2020-03-30",
      "views": 1.4245904028632075e-05
    },
    {
      "date": "2020-01-19",
      "views": 4.084764184787628e-05
    },
    {
      "date": "2021-08-19",
      "views": 1.9429117029898637e-05
    },
    {
      "date": "2020-04-16",
      "views": 2.204732632653831e-05
    },
    {
      "date": "2021-02-22",
      "views": 1.4393076354550408e-05
    },
    {
      "date": "2020-04-08",
      "views": 2.161423773067795e-05
    },
    {
      "date": "2020-04-18",
      "views": 1.408556841959218e-05
    },
    {
      "date": "2020-03-29",
      "views": 2.1071020833492963e-05
    },
    {
      "date": "2021-03-24",
      "views": 1.9583918872725892e-05
    },
    {
      "date": "2020-03-25",
      "views": 2.1376348246364552e-05
    },
    {
      "date": "2021-03-05",
      "views": 1.2197246907126677e-05
    },
    {
      "date": "2020-05-05",
      "views": 4.6010171235516504e-05
    },
    {
      "date": "2021-03-29",
      "views": 2.8276653637984285e-05
    },
    {
      "date": "2020-12-08",
      "views": 3.4295712248854184e-05
    },
    {
      "date": "2020-03-31",
      "views": 2.176171138344507e-05
    },
    {
      "date": "2019-11-30",
      "views": 3.132156106660356e-05
    },
    {
      "date": "2020-05-26",
      "views": 1.3233963909657022e-05
    },
    {
      "date": "2021-03-22",
      "views": 3.350463057101133e-05
    },
    {
      "date": "2021-02-26",
      "views": 1.4553992887948809e-05
    },
    {
      "date": "2020-04-09",
      "views": 1.4406028368794326e-05
    },
    {
      "date": "2020-04-17",
      "views": 2.6664099012687668e-05
    },
    {
      "date": "2020-05-12",
      "views": 2.0434054344075614e-05
    },
    {
      "date": "2020-05-04",
      "views": 2.7690507809300087e-05
    },
    {
      "date": "2021-03-08",
      "views": 1.864428487818797e-05
    },
    {
      "date": "2020-02-05",
      "views": 1.7774202148807492e-05
    },
    {
      "date": "2020-03-26",
      "views": 2.251358406834077e-05
    },
    {
      "date": "2019-12-01",
      "views": 3.127327171195753e-05
    },
    {
      "date": "2021-02-23",
      "views": 2.3901487628590004e-05
    },
    {
      "date": "2020-03-24",
      "views": 2.0348440265279402e-05
    },
    {
      "date": "2021-03-21",
      "views": 2.048827660812483e-05
    },
    {
      "date": "2020-05-27",
      "views": 2.029473757454692e-05
    },
    {
      "date": "2021-03-23",
      "views": 1.9276551039488016e-05
    },
    {
      "date": "2020-01-12",
      "views": 4.3570858415624164e-05
    },
    {
      "date": "2020-05-20",
      "views": 2.5417295509385195e-05
    },
    {
      "date": "2021-02-24",
      "views": 2.2091827838385657e-05
    },
    {
      "date": "2020-12-06",
      "views": 2.9125509950425674e-05
    },
    {
      "date": "2020-12-14",
      "views": 2.27441154339672e-05
    },
    {
      "date": "2019-12-18",
      "views": 1.7275334277718275e-05
    },
    {
      "date": "2020-05-19",
      "views": 1.3420337789902171e-05
    },
    {
      "date": "2021-04-04",
      "views": 1.6458938169494145e-05
    },
    {
      "date": "2021-09-21",
      "views": 5.631697697618954e-05
    },
    {
      "date": "2020-01-21",
      "views": 3.7171620465062304e-05
    },
    {
      "date": "2020-04-30",
      "views": 1.3966049697024009e-05
    },
    {
      "date": "2020-01-17",
      "views": 4.7648930788407316e-05
    },
    {
      "date": "2020-12-13",
      "views": 2.5097377825964743e-05
    },
    {
      "date": "2021-03-25",
      "views": 2.0562848789533634e-05
    },
    {
      "date": "2021-04-13",
      "views": 1.8188055715659225e-05
    },
    {
      "date": "2020-01-27",
      "views": 3.341476635652813e-05
    },
    {
      "date": "2019-01-23",
      "views": 2.767915946533633e-05
    },
    {
      "date": "2021-02-07",
      "views": 2.92554404363535e-05
    },
    {
      "date": "2021-04-15",
      "views": 1.8326417460282777e-05
    },
    {
      "date": "2019-01-22",
      "views": 2.516881372885718e-05
    },
    {
      "date": "2021-08-20",
      "views": 3.008121929208864e-05
    },
    {
      "date": "2021-04-06",
      "views": 1.7055241928606758e-05
    },
    {
      "date": "2021-04-18",
      "views": 2.4326387136206482e-05
    },
    {
      "date": "2020-01-15",
      "views": 3.6814378223558996e-05
    },
    {
      "date": "2020-12-07",
      "views": 3.4062041261218495e-05
    },
    {
      "date": "2020-05-22",
      "views": 1.0688176027133716e-05
    },
    {
      "date": "2020-12-09",
      "views": 3.442451886356057e-05
    },
    {
      "date": "2021-03-14",
      "views": 1.874346790143635e-05
    },
    {
      "date": "2020-12-10",
      "views": 3.576325386188121e-05
    },
    {
      "date": "2020-12-15",
      "views": 2.906968883264242e-05
    },
    {
      "date": "2020-05-14",
      "views": 2.1544527151490342e-05
    },
    {
      "date": "2021-04-14",
      "views": 1.637371900209387e-05
    },
    {
      "date": "2019-11-29",
      "views": 4.231286840110248e-05
    },
    {
      "date": "2020-05-13",
      "views": 1.0599323139694091e-05
    },
    {
      "date": "2020-05-07",
      "views": 2.1653223623666972e-05
    },
    {
      "date": "2019-11-18",
      "views": 2.2637706150763186e-05
    },
    {
      "date": "2020-05-25",
      "views": 1.5022766319504194e-05
    },
    {
      "date": "2019-11-17",
      "views": 3.6790185571684686e-05
    },
    {
      "date": "2020-03-27",
      "views": 2.682075188625319e-05
    },
    {
      "date": "2021-04-08",
      "views": 1.8869653822722297e-05
    },
    {
      "date": "2021-05-14",
      "views": 1.752896892759613e-05
    },
    {
      "date": "2020-03-28",
      "views": 2.3431791829121172e-05
    },
    {
      "date": "2020-03-23",
      "views": 1.8620051086649255e-05
    },
    {
      "date": "2021-04-07",
      "views": 2.197044786444108e-05
    },
    {
      "date": "2021-03-12",
      "views": 3.5214452011105356e-05
    },
    {
      "date": "2021-02-09",
      "views": 2.4060898964966503e-05
    },
    {
      "date": "2021-02-11",
      "views": 3.377762165010437e-05
    },
    {
      "date": "2021-05-17",
      "views": 1.770147903903498e-05
    },
    {
      "date": "2020-01-23",
      "views": 4.017154140882488e-05
    },
    {
      "date": "2020-01-18",
      "views": 3.187090433176995e-05
    },
    {
      "date": "2020-06-02",
      "views": 1.819914045459633e-05
    },
    {
      "date": "2020-05-18",
      "views": 1.5690783610286123e-05
    },
    {
      "date": "2021-05-13",
      "views": 1.4025955810447e-05
    },
    {
      "date": "2020-12-17",
      "views": 2.7111140525812597e-05
    },
    {
      "date": "2020-05-24",
      "views": 2.1820292435559222e-05
    },
    {
      "date": "2020-05-17",
      "views": 1.990325543543163e-05
    },
    {
      "date": "2020-12-16",
      "views": 2.038032599787171e-05
    },
    {
      "date": "2020-01-28",
      "views": 3.216860892527516e-05
    },
    {
      "date": "2020-01-22",
      "views": 3.168154794232872e-05
    },
    {
      "date": "2019-01-13",
      "views": 4.130509740819493e-05
    },
    {
      "date": "2021-03-30",
      "views": 1.891611899247706e-05
    },
    {
      "date": "2020-01-07",
      "views": 2.278657921121302e-05
    },
    {
      "date": "2020-03-08",
      "views": 1.6805338720004572e-05
    },
    {
      "date": "2019-01-14",
      "views": 1.9324738425862022e-05
    },
    {
      "date": "2020-02-06",
      "views": 3.0095221280130333e-05
    },
    {
      "date": "2021-09-20",
      "views": 6.625269321735784e-05
    },
    {
      "date": "2019-09-23",
      "views": 1.2431162437999578e-05
    },
    {
      "date": "2020-12-02",
      "views": 4.173669709028972e-05
    },
    {
      "date": "2020-03-22",
      "views": 2.419913929547803e-05
    },
    {
      "date": "2020-03-01",
      "views": 2.0104635489250875e-05
    },
    {
      "date": "2019-01-18",
      "views": 3.652230919604354e-05
    },
    {
      "date": "2021-09-19",
      "views": 3.819348629188035e-05
    },
    {
      "date": "2020-05-15",
      "views": 1.180466428518495e-05
    },
    {
      "date": "2020-02-11",
      "views": 4.811572913004798e-05
    },
    {
      "date": "2021-01-31",
      "views": 2.754080088648978e-05
    },
    {
      "date": "2021-04-05",
      "views": 2.2389255396335298e-05
    },
    {
      "date": "2020-11-30",
      "views": 5.1785642948349e-05
    },
    {
      "date": "2020-01-29",
      "views": 3.5039964001047514e-05
    },
    {
      "date": "2021-03-19",
      "views": 1.6773919105426766e-05
    },
    {
      "date": "2020-02-04",
      "views": 2.2313979028740407e-05
    },
    {
      "date": "2021-02-01",
      "views": 2.9076623364036094e-05
    },
    {
      "date": "2021-03-26",
      "views": 1.3782723631582284e-05
    },
    {
      "date": "2019-01-16",
      "views": 1.9901055570079305e-05
    },
    {
      "date": "2020-05-28",
      "views": 2.4764830844596815e-05
    },
    {
      "date": "2021-06-06",
      "views": 1.9391153050845365e-05
    },
    {
      "date": "2019-01-29",
      "views": 2.2629396630656913e-05
    },
    {
      "date": "2021-09-27",
      "views": 2.6640210182072056e-05
    },
    {
      "date": "2019-01-21",
      "views": 4.220111063393516e-05
    },
    {
      "date": "2021-04-21",
      "views": 2.3739540314575285e-05
    },
    {
      "date": "2021-04-03",
      "views": 2.3048985679994467e-05
    },
    {
      "date": "2019-09-24",
      "views": 1.835052004407988e-05
    },
    {
      "date": "2021-04-09",
      "views": 1.2951581654770257e-05
    },
    {
      "date": "2019-09-22",
      "views": 1.9548934068647624e-05
    },
    {
      "date": "2021-05-12",
      "views": 1.2151249642107726e-05
    },
    {
      "date": "2020-12-03",
      "views": 6.019147291735903e-05
    },
    {
      "date": "2019-11-12",
      "views": 2.61317212964818e-05
    },
    {
      "date": "2020-12-04",
      "views": 4.2043658134606976e-05
    },
    {
      "date": "2020-01-20",
      "views": 2.645540138985341e-05
    },
    {
      "date": "2021-02-03",
      "views": 2.548233819139954e-05
    },
    {
      "date": "2020-12-11",
      "views": 3.807696583083632e-05
    },
    {
      "date": "2020-05-08",
      "views": 2.910417967655133e-05
    },
    {
      "date": "2021-01-24",
      "views": 3.884052586694587e-05
    },
    {
      "date": "2019-11-13",
      "views": 2.786915336395096e-05
    },
    {
      "date": "2019-02-25",
      "views": 1.7444011608530673e-05
    },
    {
      "date": "2019-11-24",
      "views": 3.5472104146097774e-05
    },
    {
      "date": "2020-05-11",
      "views": 1.5434411148275173e-05
    },
    {
      "date": "2021-02-08",
      "views": 2.640924257467007e-05
    },
    {
      "date": "2021-02-25",
      "views": 2.351887767915715e-05
    },
    {
      "date": "2019-01-24",
      "views": 1.6767171889500985e-05
    },
    {
      "date": "2019-01-25",
      "views": 2.386598390859901e-05
    },
    {
      "date": "2021-04-12",
      "views": 3.077054703278114e-05
    },
    {
      "date": "2021-08-21",
      "views": 2.1710717712906153e-05
    },
    {
      "date": "2020-02-25",
      "views": 3.553576082063917e-05
    },
    {
      "date": "2021-09-28",
      "views": 4.4727039821378095e-05
    },
    {
      "date": "2019-02-13",
      "views": 2.4580059143403847e-05
    },
    {
      "date": "2019-10-27",
      "views": 1.9907169724338087e-05
    },
    {
      "date": "2021-01-14",
      "views": 1.9056062937161127e-05
    },
    {
      "date": "2020-01-14",
      "views": 2.1539936916080405e-05
    },
    {
      "date": "2020-12-05",
      "views": 3.694553981128218e-05
    },
    {
      "date": "2021-02-02",
      "views": 2.4848321702938313e-05
    },
    {
      "date": "2021-02-10",
      "views": 3.878561381250517e-05
    },
    {
      "date": "2020-05-09",
      "views": 3.074068051777013e-05
    },
    {
      "date": "2019-11-25",
      "views": 3.696687767760087e-05
    },
    {
      "date": "2019-12-03",
      "views": 2.7790927891166893e-05
    },
    {
      "date": "2019-01-11",
      "views": 2.6216152174680237e-05
    },
    {
      "date": "2021-01-28",
      "views": 5.042824886166923e-05
    },
    {
      "date": "2020-02-12",
      "views": 2.1721523857990882e-05
    },
    {
      "date": "2020-12-12",
      "views": 3.206047618244099e-05
    },
    {
      "date": "2021-01-26",
      "views": 2.863470615869891e-05
    },
    {
      "date": "2021-04-27",
      "views": 2.239213450438455e-05
    },
    {
      "date": "2019-11-10",
      "views": 3.51100433875021e-05
    },
    {
      "date": "2020-02-07",
      "views": 2.130553954680987e-05
    },
    {
      "date": "2020-03-10",
      "views": 1.765699206184442e-05
    },
    {
      "date": "2020-12-20",
      "views": 2.545750435370468e-05
    },
    {
      "date": "2019-01-17",
      "views": 3.941515082565783e-05
    },
    {
      "date": "2020-12-01",
      "views": 4.24422996935666e-05
    },
    {
      "date": "2019-02-24",
      "views": 3.615103541084296e-05
    },
    {
      "date": "2021-05-19",
      "views": 1.8444414821596396e-05
    },
    {
      "date": "2020-01-25",
      "views": 4.323791446243382e-05
    },
    {
      "date": "2019-12-04",
      "views": 2.108294028708941e-05
    },
    {
      "date": "2019-01-20",
      "views": 2.910237687048913e-05
    },
    {
      "date": "2021-03-20",
      "views": 2.9679021383734906e-05
    },
    {
      "date": "2021-03-28",
      "views": 2.3369928043991552e-05
    },
    {
      "date": "2020-03-04",
      "views": 3.145305723716345e-05
    },
    {
      "date": "2021-01-17",
      "views": 3.087652850511755e-05
    },
    {
      "date": "2021-03-31",
      "views": 1.922291371314607e-05
    },
    {
      "date": "2020-02-03",
      "views": 2.095500959440082e-05
    },
    {
      "date": "2020-02-15",
      "views": 1.6459093494851905e-05
    },
    {
      "date": "2020-05-23",
      "views": 1.2279829240203109e-05
    },
    {
      "date": "2021-01-25",
      "views": 3.087094658039952e-05
    },
    {
      "date": "2021-01-18",
      "views": 2.7410544742043144e-05
    },
    {
      "date": "2021-05-31",
      "views": 1.842983105110592e-05
    },
    {
      "date": "2020-11-17",
      "views": 2.590192667164559e-05
    },
    {
      "date": "2019-02-20",
      "views": 2.440385947037524e-05
    },
    {
      "date": "2021-04-20",
      "views": 2.622959696955082e-05
    },
    {
      "date": "2019-01-12",
      "views": 3.706118802142337e-05
    },
    {
      "date": "2021-01-09",
      "views": 1.939479018993041e-05
    },
    {
      "date": "2021-01-10",
      "views": 3.1156901574431544e-05
    },
    {
      "date": "2021-01-11",
      "views": 1.8159256681093186e-05
    },
    {
      "date": "2020-11-29",
      "views": 3.044341265436985e-05
    },
    {
      "date": "2020-01-24",
      "views": 3.9164154492283116e-05
    },
    {
      "date": "2020-11-18",
      "views": 2.9676232305546488e-05
    },
    {
      "date": "2019-02-18",
      "views": 1.732916753737239e-05
    },
    {
      "date": "2020-01-30",
      "views": 2.3972623264232247e-05
    },
    {
      "date": "2021-03-13",
      "views": 1.8164569346958963e-05
    },
    {
      "date": "2021-05-30",
      "views": 2.1650508471212493e-05
    },
    {
      "date": "2019-01-28",
      "views": 2.8770380109031023e-05
    },
    {
      "date": "2019-11-11",
      "views": 2.7742302706787777e-05
    },
    {
      "date": "2021-04-19",
      "views": 1.3900483982145236e-05
    },
    {
      "date": "2019-04-14",
      "views": 1.4499780237705773e-05
    },
    {
      "date": "2021-01-20",
      "views": 1.62237142030506e-05
    },
    {
      "date": "2019-02-04",
      "views": 2.0097913379820417e-05
    },
    {
      "date": "2019-01-26",
      "views": 1.3083222377543554e-05
    },
    {
      "date": "2020-03-09",
      "views": 9.984742362741886e-06
    },
    {
      "date": "2020-01-13",
      "views": 3.514279689806246e-05
    },
    {
      "date": "2021-05-23",
      "views": 5.859231952344913e-06
    },
    {
      "date": "2019-02-26",
      "views": 1.6184445129785763e-05
    },
    {
      "date": "2019-01-27",
      "views": 2.8507718910328078e-05
    },
    {
      "date": "2021-01-12",
      "views": 1.9380912453358304e-05
    },
    {
      "date": "2020-02-26",
      "views": 2.918864328267158e-05
    },
    {
      "date": "2021-02-04",
      "views": 3.216574651783456e-05
    },
    {
      "date": "2020-05-10",
      "views": 2.5129129458421572e-05
    },
    {
      "date": "2019-01-15",
      "views": 2.6688680226356822e-05
    },
    {
      "date": "2019-09-25",
      "views": 1.6403257686976634e-05
    },
    {
      "date": "2020-01-26",
      "views": 1.7189274322554585e-05
    },
    {
      "date": "2021-04-01",
      "views": 2.872096696867868e-05
    },
    {
      "date": "2019-01-30",
      "views": 2.819825007117784e-05
    },
    {
      "date": "2019-01-19",
      "views": 2.7744001316405027e-05
    },
    {
      "date": "2019-11-14",
      "views": 2.4618535787965475e-05
    },
    {
      "date": "2020-02-27",
      "views": 2.5311304710141754e-05
    },
    {
      "date": "2021-04-17",
      "views": 2.0342352955743885e-05
    },
    {
      "date": "2019-08-27",
      "views": 8.411722576582726e-06
    },
    {
      "date": "2021-01-08",
      "views": 2.3866720886960784e-05
    },
    {
      "date": "2020-01-08",
      "views": 3.254270067223922e-05
    },
    {
      "date": "2021-05-03",
      "views": 2.3904092954412027e-05
    },
    {
      "date": "2021-06-01",
      "views": 9.981697197048684e-06
    },
    {
      "date": "2019-11-23",
      "views": 2.286432191039833e-05
    },
    {
      "date": "2019-05-14",
      "views": 2.082861218123892e-05
    },
    {
      "date": "2021-05-16",
      "views": 1.4616174947016365e-05
    },
    {
      "date": "2021-09-17",
      "views": 3.1599087092180656e-05
    },
    {
      "date": "2021-06-07",
      "views": 1.423882785969059e-05
    },
    {
      "date": "2020-02-13",
      "views": 2.0338104938198922e-05
    },
    {
      "date": "2019-12-02",
      "views": 2.2976885253435045e-05
    },
    {
      "date": "2019-09-26",
      "views": 2.9857717313530557e-05
    },
    {
      "date": "2019-12-08",
      "views": 3.6944675348665375e-05
    },
    {
      "date": "2021-09-16",
      "views": 4.032191551092449e-05
    },
    {
      "date": "2021-05-24",
      "views": 2.341266625244257e-05
    },
    {
      "date": "2020-11-10",
      "views": 2.3587942237060785e-05
    },
    {
      "date": "2020-11-22",
      "views": 1.543512726262428e-05
    },
    {
      "date": "2021-04-16",
      "views": 1.0629581963071196e-05
    },
    {
      "date": "2020-02-10",
      "views": 2.223138424724533e-05
    },
    {
      "date": "2021-01-03",
      "views": 3.1968999757810605e-05
    },
    {
      "date": "2020-02-18",
      "views": 2.5142767191093776e-05
    },
    {
      "date": "2020-01-31",
      "views": 2.135164930253152e-05
    },
    {
      "date": "2019-01-09",
      "views": 2.346377943296492e-05
    },
    {
      "date": "2019-11-07",
      "views": 2.9816003313835795e-05
    },
    {
      "date": "2019-01-08",
      "views": 2.8709902583711796e-05
    },
    {
      "date": "2020-02-23",
      "views": 3.302550807680082e-05
    },
    {
      "date": "2019-11-19",
      "views": 2.57229382322999e-05
    },
    {
      "date": "2021-06-09",
      "views": 1.5913747488611723e-05
    },
    {
      "date": "2021-09-15",
      "views": 4.965489845573266e-05
    },
    {
      "date": "2021-04-02",
      "views": 1.5206604532480547e-05
    },
    {
      "date": "2021-01-15",
      "views": 1.5112132019585323e-05
    },
    {
      "date": "2020-11-21",
      "views": 1.960944265257715e-05
    },
    {
      "date": "2020-03-03",
      "views": 3.329952638559329e-05
    },
    {
      "date": "2021-09-12",
      "views": 3.1872725446411326e-05
    },
    {
      "date": "2021-09-07",
      "views": 1.772869314338127e-05
    },
    {
      "date": "2019-08-28",
      "views": 1.4767267858549263e-05
    },
    {
      "date": "2020-12-27",
      "views": 2.2184486187132193e-05
    },
    {
      "date": "2020-01-09",
      "views": 4.086561149063156e-05
    },
    {
      "date": "2020-11-25",
      "views": 3.659435505934385e-05
    },
    {
      "date": "2019-05-05",
      "views": 2.057837767228128e-05
    },
    {
      "date": "2019-12-10",
      "views": 2.987708566955545e-05
    },
    {
      "date": "2021-05-27",
      "views": 2.2201911584587434e-05
    },
    {
      "date": "2021-06-15",
      "views": 4.460441700087657e-05
    },
    {
      "date": "2019-03-19",
      "views": 3.765461928042023e-05
    },
    {
      "date": "2019-05-12",
      "views": 2.009690361525026e-05
    },
    {
      "date": "2021-06-02",
      "views": 9.639055912307724e-06
    },
    {
      "date": "2019-10-30",
      "views": 2.1678471110340322e-05
    },
    {
      "date": "2021-05-20",
      "views": 1.733385499982666e-05
    },
    {
      "date": "2019-02-22",
      "views": 1.6190005909352156e-05
    },
    {
      "date": "2020-01-11",
      "views": 2.876814790663777e-05
    },
    {
      "date": "2020-05-29",
      "views": 1.311003162139627e-05
    },
    {
      "date": "2020-11-23",
      "views": 1.980134941891649e-05
    },
    {
      "date": "2020-12-21",
      "views": 1.9726220819468742e-05
    },
    {
      "date": "2020-02-09",
      "views": 2.4097667847787082e-05
    },
    {
      "date": "2020-11-27",
      "views": 1.964256425819365e-05
    },
    {
      "date": "2020-01-10",
      "views": 4.008100582229348e-05
    },
    {
      "date": "2021-09-29",
      "views": 3.231092340003231e-05
    },
    {
      "date": "2021-04-11",
      "views": 2.4548040939360415e-05
    },
    {
      "date": "2019-11-28",
      "views": 3.429191355112509e-05
    },
    {
      "date": "2020-02-14",
      "views": 1.871459821837025e-05
    },
    {
      "date": "2019-10-13",
      "views": 1.391210545804002e-05
    },
    {
      "date": "2021-05-18",
      "views": 2.455489861457754e-05
    },
    {
      "date": "2021-04-26",
      "views": 1.2034396155658433e-05
    },
    {
      "date": "2020-11-19",
      "views": 2.727349363535835e-05
    },
    {
      "date": "2019-02-12",
      "views": 1.745920748062717e-05
    },
    {
      "date": "2020-02-20",
      "views": 2.4622631409913286e-05
    },
    {
      "date": "2019-02-09",
      "views": 2.0310971666194527e-05
    },
    {
      "date": "2021-02-12",
      "views": 3.224700029608609e-05
    },
    {
      "date": "2021-02-13",
      "views": 3.261628469939507e-05
    },
    {
      "date": "2021-09-22",
      "views": 3.902099861830191e-05
    },
    {
      "date": "2019-02-19",
      "views": 2.705363070129254e-05
    },
    {
      "date": "2020-11-16",
      "views": 3.192301587371964e-05
    },
    {
      "date": "2020-11-09",
      "views": 2.0763374916710552e-05
    },
    {
      "date": "2019-12-05",
      "views": 4.226243492905722e-05
    },
    {
      "date": "2019-10-28",
      "views": 2.6461466812028326e-05
    },
    {
      "date": "2020-10-12",
      "views": 2.7546034013842802e-05
    },
    {
      "date": "2021-08-22",
      "views": 1.48758098734183e-05
    },
    {
      "date": "2019-09-17",
      "views": 1.7542248441577606e-05
    },
    {
      "date": "2021-04-25",
      "views": 2.9863341495980008e-05
    },
    {
      "date": "2020-03-21",
      "views": 1.916760460145183e-05
    },
    {
      "date": "2020-10-13",
      "views": 1.8335065997070056e-05
    },
    {
      "date": "2021-01-22",
      "views": 3.32208059953784e-05
    },
    {
      "date": "2019-01-10",
      "views": 2.896958097432426e-05
    },
    {
      "date": "2019-12-17",
      "views": 2.3478082231983017e-05
    },
    {
      "date": "2021-04-22",
      "views": 1.553970302713415e-05
    },
    {
      "date": "2020-05-31",
      "views": 1.8791117933056147e-05
    },
    {
      "date": "2021-01-23",
      "views": 2.3513160021749673e-05
    },
    {
      "date": "2020-11-28",
      "views": 2.1717327268276117e-05
    },
    {
      "date": "2020-05-16",
      "views": 1.5390166367698436e-05
    },
    {
      "date": "2020-11-26",
      "views": 3.008790827142388e-05
    },
    {
      "date": "2021-01-02",
      "views": 2.1885669263766085e-05
    },
    {
      "date": "2020-06-01",
      "views": 9.186348869430641e-06
    },
    {
      "date": "2019-03-03",
      "views": 2.3255876357449974e-05
    },
    {
      "date": "2020-11-24",
      "views": 1.546844909032629e-05
    },
    {
      "date": "2020-11-04",
      "views": 1.7756454249163892e-05
    },
    {
      "date": "2021-06-14",
      "views": 1.95773830324779e-05
    },
    {
      "date": "2019-02-03",
      "views": 2.1846297052649575e-05
    },
    {
      "date": "2021-08-29",
      "views": 2.441915705069861e-05
    },
    {
      "date": "2021-01-16",
      "views": 3.507780451919048e-05
    },
    {
      "date": "2019-04-03",
      "views": 1.6547463641545166e-05
    },
    {
      "date": "2021-09-14",
      "views": 3.949879618441629e-05
    },
    {
      "date": "2019-02-05",
      "views": 2.714504345547043e-05
    },
    {
      "date": "2020-12-28",
      "views": 1.4420922317819379e-05
    },
    {
      "date": "2020-03-12",
      "views": 2.6543748691954692e-05
    },
    {
      "date": "2021-06-10",
      "views": 1.6887713592324634e-05
    },
    {
      "date": "2019-10-09",
      "views": 1.2558501687025394e-05
    },
    {
      "date": "2021-09-09",
      "views": 2.3207736159602386e-05
    },
    {
      "date": "2021-01-19",
      "views": 2.9274059972161312e-05
    },
    {
      "date": "2019-04-15",
      "views": 1.9021387648271718e-05
    },
    {
      "date": "2020-10-15",
      "views": 1.9197308188350026e-05
    },
    {
      "date": "2021-01-29",
      "views": 1.2334223294983387e-05
    },
    {
      "date": "2021-05-05",
      "views": 1.034820681098276e-05
    },
    {
      "date": "2019-11-09",
      "views": 4.0569996151997333e-05
    },
    {
      "date": "2019-05-13",
      "views": 2.1645685383570563e-05
    },
    {
      "date": "2021-09-13",
      "views": 3.624690274863052e-05
    },
    {
      "date": "2020-10-16",
      "views": 1.828698300278715e-05
    },
    {
      "date": "2021-06-08",
      "views": 2.1072373065292747e-05
    },
    {
      "date": "2020-12-26",
      "views": 2.176624360344516e-05
    },
    {
      "date": "2019-10-15",
      "views": 1.6457586741768122e-05
    },
    {
      "date": "2021-01-04",
      "views": 4.6322823758774905e-05
    },
    {
      "date": "2019-12-09",
      "views": 2.6769488960159793e-05
    },
    {
      "date": "2020-12-25",
      "views": 2.415271234959686e-05
    },
    {
      "date": "2021-04-23",
      "views": 2.36265818734895e-05
    },
    {
      "date": "2021-05-10",
      "views": 1.6597938904831107e-05
    },
    {
      "date": "2019-02-21",
      "views": 2.9591770951238045e-05
    },
    {
      "date": "2021-04-28",
      "views": 1.4644960394535233e-05
    },
    {
      "date": "2019-11-22",
      "views": 2.1326205641492267e-05
    },
    {
      "date": "2019-04-09",
      "views": 1.8060843369141965e-05
    },
    {
      "date": "2021-05-26",
      "views": 2.310747471349042e-05
    },
    {
      "date": "2019-02-15",
      "views": 1.635267821097612e-05
    },
    {
      "date": "2019-11-06",
      "views": 2.717976697879777e-05
    },
    {
      "date": "2021-09-08",
      "views": 2.0818643366682388e-05
    },
    {
      "date": "2019-05-16",
      "views": 1.502157003572317e-05
    },
    {
      "date": "2019-03-14",
      "views": 3.4553314363252456e-05
    },
    {
      "date": "2021-05-09",
      "views": 3.876676307929127e-05
    },
    {
      "date": "2019-09-29",
      "views": 1.0970975188042514e-05
    },
    {
      "date": "2019-04-07",
      "views": 2.1025489583303466e-05
    },
    {
      "date": "2019-05-07",
      "views": 2.254581732815155e-05
    },
    {
      "date": "2020-10-08",
      "views": 8.402380674524448e-06
    },
    {
      "date": "2019-09-18",
      "views": 1.931638303777573e-05
    },
    {
      "date": "2021-05-11",
      "views": 1.2395929530911465e-05
    },
    {
      "date": "2020-12-18",
      "views": 2.2200836488908753e-05
    },
    {
      "date": "2020-10-19",
      "views": 1.8093423583330166e-05
    },
    {
      "date": "2019-01-03",
      "views": 2.1868526419167963e-05
    },
    {
      "date": "2021-01-30",
      "views": 2.3836345867451263e-05
    },
    {
      "date": "2021-01-21",
      "views": 2.932734424815096e-05
    },
    {
      "date": "2021-08-25",
      "views": 2.78097590006285e-05
    },
    {
      "date": "2020-12-23",
      "views": 4.425899923763874e-06
    },
    {
      "date": "2021-06-13",
      "views": 1.0155831071968281e-05
    },
    {
      "date": "2020-12-19",
      "views": 2.1076969932648544e-05
    },
    {
      "date": "2020-11-20",
      "views": 2.008541508741991e-05
    },
    {
      "date": "2020-11-11",
      "views": 2.0853926585836848e-05
    },
    {
      "date": "2019-12-06",
      "views": 2.5504813122590705e-05
    },
    {
      "date": "2021-01-13",
      "views": 2.8243002796057277e-05
    },
    {
      "date": "2020-03-02",
      "views": 3.774027145186824e-05
    },
    {
      "date": "2020-02-28",
      "views": 1.8438977829840775e-05
    },
    {
      "date": "2021-05-25",
      "views": 2.0077998242697106e-05
    },
    {
      "date": "2021-09-30",
      "views": 3.869573268987858e-05
    },
    {
      "date": "2020-02-24",
      "views": 2.386079611546239e-05
    },
    {
      "date": "2020-11-03",
      "views": 2.1325921390876594e-05
    },
    {
      "date": "2019-08-12",
      "views": 1.4752091108914689e-05
    },
    {
      "date": "2020-02-16",
      "views": 2.1357253457205404e-05
    },
    {
      "date": "2019-11-04",
      "views": 2.4230186774356384e-05
    },
    {
      "date": "2020-11-05",
      "views": 3.192417006279028e-05
    },
    {
      "date": "2019-10-14",
      "views": 1.4752122198150506e-05
    },
    {
      "date": "2020-02-08",
      "views": 1.7735134631840773e-05
    },
    {
      "date": "2020-11-15",
      "views": 2.9647527952059948e-05
    },
    {
      "date": "2019-02-23",
      "views": 2.1422013669284914e-05
    },
    {
      "date": "2020-12-22",
      "views": 2.117683931437865e-05
    },
    {
      "date": "2019-09-30",
      "views": 2.6987700355562953e-05
    },
    {
      "date": "2020-02-01",
      "views": 2.490908185124296e-05
    },
    {
      "date": "2020-06-07",
      "views": 2.5865365151481074e-05
    },
    {
      "date": "2019-09-09",
      "views": 1.928970061507841e-05
    },
    {
      "date": "2019-09-16",
      "views": 1.5311887843483923e-05
    },
    {
      "date": "2021-09-23",
      "views": 3.9176893468232436e-05
    },
    {
      "date": "2019-10-03",
      "views": 2.3370563657350956e-05
    },
    {
      "date": "2021-05-15",
      "views": 2.1611697485633367e-05
    },
    {
      "date": "2019-02-06",
      "views": 1.7382688580442737e-05
    },
    {
      "date": "2021-01-07",
      "views": 2.5748778930750878e-05
    },
    {
      "date": "2019-10-20",
      "views": 2.0467807908545527e-05
    },
    {
      "date": "2021-06-17",
      "views": 1.8618731100618908e-05
    },
    {
      "date": "2019-02-14",
      "views": 1.4931375398667723e-05
    },
    {
      "date": "2019-08-26",
      "views": 1.9989393862785747e-05
    },
    {
      "date": "2021-05-06",
      "views": 1.7175638074954483e-05
    },
    {
      "date": "2021-08-18",
      "views": 2.4544355385191643e-05
    },
    {
      "date": "2021-08-23",
      "views": 3.0954223465682484e-05
    },
    {
      "date": "2020-02-19",
      "views": 3.2665042851092046e-05
    },
    {
      "date": "2019-03-13",
      "views": 3.77594117636224e-05
    },
    {
      "date": "2020-01-05",
      "views": 3.2147557287951696e-05
    },
    {
      "date": "2019-02-27",
      "views": 1.844883917268377e-05
    },
    {
      "date": "2019-05-15",
      "views": 1.11314879181613e-05
    },
    {
      "date": "2019-04-02",
      "views": 1.8474151744737784e-05
    },
    {
      "date": "2021-09-26",
      "views": 2.5744511468189687e-05
    },
    {
      "date": "2020-10-25",
      "views": 2.8486153891392405e-05
    },
    {
      "date": "2020-06-09",
      "views": 1.409119387098103e-05
    },
    {
      "date": "2020-01-06",
      "views": 3.0964019808981966e-05
    },
    {
      "date": "2020-02-22",
      "views": 1.932883464181964e-05
    },
    {
      "date": "2021-05-07",
      "views": 2.929903114382371e-05
    },
    {
      "date": "2019-01-31",
      "views": 2.2965254526786577e-05
    },
    {
      "date": "2019-10-21",
      "views": 1.569104951153763e-05
    },
    {
      "date": "2019-11-03",
      "views": 2.2604675057796045e-05
    },
    {
      "date": "2019-10-29",
      "views": 2.096310807425552e-05
    },
    {
      "date": "2019-10-22",
      "views": 2.431323052008114e-05
    },
    {
      "date": "2021-02-06",
      "views": 2.3955763079586254e-05
    },
    {
      "date": "2019-12-07",
      "views": 2.2144443282544643e-05
    },
    {
      "date": "2020-03-20",
      "views": 2.2252039955762945e-05
    },
    {
      "date": "2019-03-20",
      "views": 2.632251534560189e-05
    },
    {
      "date": "2019-04-08",
      "views": 1.8190797821106238e-05
    },
    {
      "date": "2019-11-20",
      "views": 3.291999273636289e-05
    },
    {
      "date": "2020-10-27",
      "views": 2.4289077388737343e-05
    },
    {
      "date": "2020-10-20",
      "views": 2.285311026260052e-05
    },
    {
      "date": "2020-06-04",
      "views": 1.5508380211720406e-05
    },
    {
      "date": "2019-02-10",
      "views": 1.7961552823508836e-05
    },
    {
      "date": "2021-08-30",
      "views": 1.6466117796073464e-05
    },
    {
      "date": "2019-11-26",
      "views": 3.438066269738545e-05
    },
    {
      "date": "2019-03-10",
      "views": 2.7357096902610623e-05
    },
    {
      "date": "2020-02-17",
      "views": 2.5942209779987503e-05
    },
    {
      "date": "2019-03-18",
      "views": 2.6627714124861155e-05
    },
    {
      "date": "2019-08-25",
      "views": 2.060169055048929e-05
    },
    {
      "date": "2020-11-01",
      "views": 2.3989300771855752e-05
    },
    {
      "date": "2019-03-05",
      "views": 2.6860780574283487e-05
    },
    {
      "date": "2020-09-15",
      "views": 7.202542703361221e-06
    },
    {
      "date": "2020-10-26",
      "views": 1.859982385966805e-05
    },
    {
      "date": "2019-11-21",
      "views": 3.023333415448562e-05
    },
    {
      "date": "2021-05-29",
      "views": 1.9807886801422438e-05
    },
    {
      "date": "2019-12-15",
      "views": 3.155181280940496e-05
    },
    {
      "date": "2019-04-17",
      "views": 1.7855070393615027e-05
    },
    {
      "date": "2019-11-08",
      "views": 2.965250818705751e-05
    },
    {
      "date": "2021-05-08",
      "views": 2.1305925390910466e-05
    },
    {
      "date": "2019-03-11",
      "views": 2.7349353584794465e-05
    },
    {
      "date": "2020-12-24",
      "views": 1.608180708049802e-05
    },
    {
      "date": "2020-08-25",
      "views": 3.152494016829064e-05
    },
    {
      "date": "2021-08-24",
      "views": 2.1791989723356424e-05
    },
    {
      "date": "2020-11-02",
      "views": 1.989588397412497e-05
    },
    {
      "date": "2020-03-19",
      "views": 2.98285798613128e-05
    },
    {
      "date": "2019-04-04",
      "views": 2.0658108307510697e-05
    },
    {
      "date": "2020-06-03",
      "views": 1.7836351475214903e-05
    },
    {
      "date": "2019-10-07",
      "views": 1.0908313443841821e-05
    },
    {
      "date": "2020-10-18",
      "views": 2.646959712255118e-05
    },
    {
      "date": "2019-12-22",
      "views": 3.581163920405472e-05
    },
    {
      "date": "2020-10-29",
      "views": 2.1602065533153066e-05
    },
    {
      "date": "2019-10-10",
      "views": 2.4004241445097083e-05
    },
    {
      "date": "2020-10-14",
      "views": 1.09657840124352e-05
    },
    {
      "date": "2019-02-17",
      "views": 1.7722418964239286e-05
    },
    {
      "date": "2020-10-07",
      "views": 1.6093082388535288e-05
    },
    {
      "date": "2020-11-14",
      "views": 1.8303856945667693e-05
    },
    {
      "date": "2019-09-19",
      "views": 3.57326024264539e-05
    },
    {
      "date": "2020-03-13",
      "views": 4.485202282622946e-05
    },
    {
      "date": "2019-05-20",
      "views": 1.902846372746673e-05
    },
    {
      "date": "2019-10-04",
      "views": 2.3318262372179104e-05
    },
    {
      "date": "2020-09-17",
      "views": 1.2618256724742193e-05
    },
    {
      "date": "2020-10-28",
      "views": 2.423092443772606e-05
    },
    {
      "date": "2019-02-07",
      "views": 2.475313696504758e-05
    },
    {
      "date": "2019-02-08",
      "views": 1.9634752271430816e-05
    },
    {
      "date": "2021-08-26",
      "views": 1.8203574211117773e-05
    },
    {
      "date": "2019-10-16",
      "views": 2.0704319542186087e-05
    },
    {
      "date": "2021-09-06",
      "views": 1.635127934333262e-05
    },
    {
      "date": "2021-06-20",
      "views": 2.3043699633056516e-05
    },
    {
      "date": "2019-04-29",
      "views": 1.3839091814922373e-05
    },
    {
      "date": "2019-12-12",
      "views": 3.194364289562734e-05
    },
    {
      "date": "2019-04-18",
      "views": 1.2468672460443137e-05
    },
    {
      "date": "2020-11-08",
      "views": 3.397906501263051e-05
    },
    {
      "date": "2020-03-18",
      "views": 2.118483236618689e-05
    },
    {
      "date": "2019-04-12",
      "views": 2.3804115930011933e-05
    },
    {
      "date": "2021-01-05",
      "views": 1.947813741393098e-05
    },
    {
      "date": "2020-02-21",
      "views": 2.4278747771557792e-05
    },
    {
      "date": "2020-09-27",
      "views": 2.3754261399555105e-05
    },
    {
      "date": "2020-09-14",
      "views": 1.935360980474245e-05
    },
    {
      "date": "2019-11-16",
      "views": 2.4560278906527263e-05
    },
    {
      "date": "2019-03-28",
      "views": 2.7695378531531683e-05
    },
    {
      "date": "2020-06-25",
      "views": 1.4990910057265277e-05
    },
    {
      "date": "2019-11-27",
      "views": 3.9943751004995016e-05
    },
    {
      "date": "2020-10-21",
      "views": 1.4331055014053989e-05
    },
    {
      "date": "2019-11-15",
      "views": 2.1696706560481378e-05
    },
    {
      "date": "2021-05-28",
      "views": 1.8689589794653322e-05
    },
    {
      "date": "2019-04-23",
      "views": 1.7102288789248496e-05
    },
    {
      "date": "2019-05-09",
      "views": 2.2513585541775365e-05
    },
    {
      "date": "2020-11-12",
      "views": 2.8784065141537646e-05
    },
    {
      "date": "2019-04-11",
      "views": 1.8096157552386113e-05
    },
    {
      "date": "2020-10-11",
      "views": 1.933296958709073e-05
    },
    {
      "date": "2021-06-03",
      "views": 1.8699204594886655e-05
    },
    {
      "date": "2019-03-12",
      "views": 1.978734005982972e-05
    },
    {
      "date": "2019-04-10",
      "views": 1.89100797343512e-05
    },
    {
      "date": "2019-04-05",
      "views": 2.4393477396261433e-05
    },
    {
      "date": "2020-06-16",
      "views": 2.1073952009928172e-05
    },
    {
      "date": "2019-02-16",
      "views": 2.9403016975718763e-05
    },
    {
      "date": "2019-12-13",
      "views": 3.653519679074832e-05
    },
    {
      "date": "2019-05-03",
      "views": 2.5610818009527225e-05
    },
    {
      "date": "2019-05-06",
      "views": 2.5329527409471294e-05
    },
    {
      "date": "2019-12-24",
      "views": 3.5444770954782444e-05
    },
    {
      "date": "2019-05-21",
      "views": 1.3675988480910274e-05
    },
    {
      "date": "2021-03-27",
      "views": 3.0691086541191275e-05
    },
    {
      "date": "2019-08-02",
      "views": 1.8496505393580973e-05
    },
    {
      "date": "2021-08-17",
      "views": 2.210722001708285e-05
    },
    {
      "date": "2021-01-06",
      "views": 1.9761941413124426e-05
    },
    {
      "date": "2019-09-08",
      "views": 1.6899742278930245e-05
    },
    {
      "date": "2020-06-10",
      "views": 1.8229175044044903e-05
    },
    {
      "date": "2019-02-11",
      "views": 2.4404850182379323e-05
    },
    {
      "date": "2019-09-11",
      "views": 1.4188393488743537e-05
    },
    {
      "date": "2020-02-29",
      "views": 1.945970695970696e-05
    },
    {
      "date": "2020-10-22",
      "views": 2.1128312240234948e-05
    },
    {
      "date": "2021-06-18",
      "views": 2.43107891282151e-05
    },
    {
      "date": "2019-10-06",
      "views": 2.6525902543834053e-05
    },
    {
      "date": "2020-10-24",
      "views": 3.1624415357252296e-05
    },
    {
      "date": "2019-05-29",
      "views": 1.7686988706392263e-05
    },
    {
      "date": "2021-04-10",
      "views": 2.6682557612088976e-05
    },
    {
      "date": "2019-05-27",
      "views": 1.5211193156484199e-05
    },
    {
      "date": "2020-06-05",
      "views": 1.8621443578121337e-05
    },
    {
      "date": "2019-11-05",
      "views": 3.080550227344607e-05
    },
    {
      "date": "2020-10-04",
      "views": 1.6406335716695395e-05
    },
    {
      "date": "2019-03-26",
      "views": 2.6332891003461836e-05
    },
    {
      "date": "2019-03-21",
      "views": 2.6830434528469486e-05
    },
    {
      "date": "2020-11-13",
      "views": 3.328737527972133e-05
    },
    {
      "date": "2019-06-24",
      "views": 2.750448380387011e-05
    },
    {
      "date": "2019-03-04",
      "views": 2.6409986747845936e-05
    },
    {
      "date": "2020-07-19",
      "views": 3.175473116091769e-05
    },
    {
      "date": "2019-10-23",
      "views": 1.2442595566910576e-05
    },
    {
      "date": "2019-05-08",
      "views": 7.99392461729086e-06
    },
    {
      "date": "2019-01-07",
      "views": 2.8991908699363288e-05
    },
    {
      "date": "2020-05-30",
      "views": 2.161122487019758e-05
    },
    {
      "date": "2019-12-16",
      "views": 3.8073884488064895e-05
    },
    {
      "date": "2021-05-04",
      "views": 1.609465265224787e-05
    },
    {
      "date": "2019-02-01",
      "views": 2.8879436603448205e-05
    },
    {
      "date": "2019-10-01",
      "views": 2.141716236125342e-05
    },
    {
      "date": "2020-10-06",
      "views": 2.4476370417858713e-05
    },
    {
      "date": "2019-09-21",
      "views": 2.3536727824995757e-05
    },
    {
      "date": "2021-06-11",
      "views": 1.3554022946960849e-05
    },
    {
      "date": "2019-09-12",
      "views": 1.69808297045654e-05
    },
    {
      "date": "2019-04-16",
      "views": 1.851810339534299e-05
    },
    {
      "date": "2021-08-28",
      "views": 1.8958985789055214e-05
    },
    {
      "date": "2020-06-08",
      "views": 2.0720122401396756e-05
    },
    {
      "date": "2021-09-18",
      "views": 5.348958234665484e-05
    },
    {
      "date": "2019-09-15",
      "views": 1.761816868463789e-05
    },
    {
      "date": "2020-08-30",
      "views": 2.0084530768873496e-05
    },
    {
      "date": "2021-06-16",
      "views": 3.7455872300446034e-05
    },
    {
      "date": "2021-09-05",
      "views": 1.9788657141726364e-05
    },
    {
      "date": "2019-03-27",
      "views": 2.48671520224646e-05
    },
    {
      "date": "2020-10-17",
      "views": 2.329184796412612e-05
    },
    {
      "date": "2021-08-27",
      "views": 1.5523796786335238e-05
    },
    {
      "date": "2019-02-28",
      "views": 3.0462670852745355e-05
    },
    {
      "date": "2019-08-20",
      "views": 2.462696307679426e-05
    },
    {
      "date": "2020-06-15",
      "views": 2.156874257825559e-05
    },
    {
      "date": "2020-09-28",
      "views": 2.335217075107253e-05
    },
    {
      "date": "2019-08-13",
      "views": 1.9293519547952837e-05
    },
    {
      "date": "2019-05-01",
      "views": 2.8236438907206375e-05
    },
    {
      "date": "2019-09-20",
      "views": 2.2185547594778507e-05
    },
    {
      "date": "2021-09-10",
      "views": 1.8614082977202127e-05
    },
    {
      "date": "2019-04-21",
      "views": 1.917402558667192e-05
    },
    {
      "date": "2021-08-31",
      "views": 3.446189662962651e-05
    },
    {
      "date": "2021-06-24",
      "views": 1.9578667084344897e-05
    },
    {
      "date": "2019-05-22",
      "views": 1.2688002030080325e-05
    },
    {
      "date": "2019-09-04",
      "views": 1.827047394684152e-05
    },
    {
      "date": "2020-01-04",
      "views": 2.6851554537185486e-05
    },
    {
      "date": "2020-07-17",
      "views": 0.0001393332776000223
    },
    {
      "date": "2020-03-17",
      "views": 1.9649367945331092e-05
    },
    {
      "date": "2020-09-23",
      "views": 9.616853856946093e-06
    },
    {
      "date": "2019-06-11",
      "views": 1.2167102992498982e-05
    },
    {
      "date": "2019-02-02",
      "views": 1.9680023533164984e-05
    },
    {
      "date": "2019-09-03",
      "views": 1.340229558986295e-05
    },
    {
      "date": "2019-12-21",
      "views": 3.81496406939674e-05
    },
    {
      "date": "2021-09-02",
      "views": 1.7418530267962317e-05
    },
    {
      "date": "2019-04-22",
      "views": 2.051762734157422e-05
    },
    {
      "date": "2020-07-18",
      "views": 5.5235649087921347e-05
    },
    {
      "date": "2021-08-15",
      "views": 2.4283171339945393e-05
    },
    {
      "date": "2021-09-01",
      "views": 9.643422402393498e-06
    },
    {
      "date": "2019-03-01",
      "views": 1.7534178755795304e-05
    },
    {
      "date": "2019-04-13",
      "views": 2.0676985171500083e-05
    },
    {
      "date": "2019-06-04",
      "views": 3.687591158709071e-05
    },
    {
      "date": "2021-06-27",
      "views": 1.3828883697935693e-05
    },
    {
      "date": "2020-11-06",
      "views": 2.2499357161223966e-05
    },
    {
      "date": "2019-10-12",
      "views": 2.218544947720641e-05
    },
    {
      "date": "2019-03-24",
      "views": 2.930918256689821e-05
    },
    {
      "date": "2019-12-25",
      "views": 2.5001875140635547e-05
    },
    {
      "date": "2020-01-02",
      "views": 2.3138619817862526e-05
    },
    {
      "date": "2021-04-24",
      "views": 1.773149856651916e-05
    },
    {
      "date": "2021-05-21",
      "views": 2.4937033989177326e-05
    },
    {
      "date": "2021-06-05",
      "views": 1.6849037438561187e-05
    },
    {
      "date": "2019-03-06",
      "views": 2.0878757057765556e-05
    },
    {
      "date": "2019-09-27",
      "views": 2.4405313165125065e-05
    },
    {
      "date": "2020-08-09",
      "views": 2.3070627691067296e-05
    },
    {
      "date": "2020-08-26",
      "views": 2.393577328035549e-05
    },
    {
      "date": "2021-07-18",
      "views": 4.342439992907348e-05
    },
    {
      "date": "2019-06-02",
      "views": 1.5144539484843345e-05
    },
    {
      "date": "2021-06-23",
      "views": 3.987835814367529e-05
    },
    {
      "date": "2021-06-19",
      "views": 2.8942285308015127e-05
    },
    {
      "date": "2019-06-05",
      "views": 1.5179847992797162e-05
    },
    {
      "date": "2020-09-29",
      "views": 2.1309050486467866e-05
    },
    {
      "date": "2019-06-09",
      "views": 2.1289149224770838e-05
    },
    {
      "date": "2019-12-14",
      "views": 2.774106989740848e-05
    },
    {
      "date": "2019-03-09",
      "views": 4.184038909300214e-05
    },
    {
      "date": "2019-06-17",
      "views": 1.926062731863177e-05
    },
    {
      "date": "2020-08-18",
      "views": 1.7865203466802284e-05
    },
    {
      "date": "2020-09-21",
      "views": 1.155186735935864e-05
    },
    {
      "date": "2019-10-11",
      "views": 2.3875285560981248e-05
    },
    {
      "date": "2020-08-06",
      "views": 1.205063193513868e-05
    },
    {
      "date": "2019-06-03",
      "views": 3.6203132842992885e-05
    },
    {
      "date": "2019-05-04",
      "views": 3.110462906001811e-05
    },
    {
      "date": "2019-05-28",
      "views": 1.2037716945123752e-05
    },
    {
      "date": "2020-09-08",
      "views": 1.138638560926479e-05
    },
    {
      "date": "2020-09-30",
      "views": 1.991869378897187e-05
    },
    {
      "date": "2019-08-29",
      "views": 2.0223073988138495e-05
    },
    {
      "date": "2020-08-24",
      "views": 2.118770318676298e-05
    },
    {
      "date": "2020-07-16",
      "views": 3.1864738342008395e-05
    },
    {
      "date": "2019-06-19",
      "views": 1.7879492222420883e-05
    },
    {
      "date": "2019-09-05",
      "views": 1.399152328942865e-05
    },
    {
      "date": "2020-10-05",
      "views": 1.9442354391347375e-05
    },
    {
      "date": "2019-03-25",
      "views": 2.5550038275922726e-05
    },
    {
      "date": "2021-06-21",
      "views": 1.7132831988596386e-05
    },
    {
      "date": "2019-06-18",
      "views": 1.540999841790683e-05
    },
    {
      "date": "2020-09-24",
      "views": 1.1108494443531079e-05
    },
    {
      "date": "2021-07-19",
      "views": 2.277425901417824e-05
    },
    {
      "date": "2019-12-23",
      "views": 3.310260815449649e-05
    },
    {
      "date": "2021-01-01",
      "views": 6.0502875701682105e-06
    },
    {
      "date": "2021-08-10",
      "views": 1.7329735350184437e-05
    },
    {
      "date": "2019-04-30",
      "views": 2.178347875620693e-05
    },
    {
      "date": "2020-06-11",
      "views": 1.9288518870801884e-05
    },
    {
      "date": "2019-09-13",
      "views": 1.095101004816011e-05
    },
    {
      "date": "2020-12-30",
      "views": 2.1767522855899e-05
    },
    {
      "date": "2019-05-02",
      "views": 2.1367425247749673e-05
    },
    {
      "date": "2020-09-13",
      "views": 2.0853226213602888e-05
    },
    {
      "date": "2019-01-06",
      "views": 2.0917063841866997e-05
    },
    {
      "date": "2019-03-22",
      "views": 1.3103183199972046e-05
    },
    {
      "date": "2019-03-29",
      "views": 2.3474099684441033e-05
    },
    {
      "date": "2021-07-06",
      "views": 1.9740972124431294e-05
    },
    {
      "date": "2020-08-05",
      "views": 2.2770744147918755e-05
    },
    {
      "date": "2021-05-02",
      "views": 4.19321088475727e-05
    },
    {
      "date": "2019-03-02",
      "views": 2.3645642108159468e-05
    },
    {
      "date": "2020-10-01",
      "views": 2.141902029401175e-05
    },
    {
      "date": "2019-06-23",
      "views": 3.3200806779604746e-05
    },
    {
      "date": "2019-10-05",
      "views": 3.463665507407754e-05
    },
    {
      "date": "2019-01-05",
      "views": 2.4831469893462197e-05
    },
    {
      "date": "2019-01-04",
      "views": 1.6398718440153904e-05
    },
    {
      "date": "2019-09-28",
      "views": 1.6107404171012312e-05
    },
    {
      "date": "2020-08-02",
      "views": 1.588451711678908e-05
    },
    {
      "date": "2020-03-15",
      "views": 2.8836911246395388e-05
    },
    {
      "date": "2021-04-30",
      "views": 1.46572349239064e-05
    },
    {
      "date": "2020-01-03",
      "views": 3.260124140869964e-05
    },
    {
      "date": "2020-07-25",
      "views": 2.7641871907565582e-05
    },
    {
      "date": "2019-06-14",
      "views": 2.5847744476583173e-05
    },
    {
      "date": "2021-06-12",
      "views": 1.4583903017044936e-05
    },
    {
      "date": "2019-03-07",
      "views": 1.6470665744309385e-05
    },
    {
      "date": "2019-03-17",
      "views": 2.932889421978062e-05
    },
    {
      "date": "2020-06-12",
      "views": 1.9776759933866514e-05
    },
    {
      "date": "2020-08-23",
      "views": 2.4949446184668315e-05
    },
    {
      "date": "2020-06-14",
      "views": 1.5160435306632438e-05
    },
    {
      "date": "2020-07-05",
      "views": 2.0002987112742168e-05
    },
    {
      "date": "2020-09-16",
      "views": 1.908012592883113e-05
    },
    {
      "date": "2019-01-02",
      "views": 2.7089552643127652e-05
    },
    {
      "date": "2019-09-10",
      "views": 1.8894981691757215e-05
    },
    {
      "date": "2021-09-24",
      "views": 2.9356781181598698e-05
    },
    {
      "date": "2019-09-07",
      "views": 8.695662975978853e-06
    },
    {
      "date": "2019-05-30",
      "views": 3.0108511073910372e-05
    },
    {
      "date": "2020-09-26",
      "views": 1.828438805810047e-05
    },
    {
      "date": "2019-10-02",
      "views": 2.1779499759279213e-05
    },
    {
      "date": "2019-10-08",
      "views": 2.0798714420514975e-05
    },
    {
      "date": "2020-06-06",
      "views": 2.4892464553130476e-05
    },
    {
      "date": "2019-08-24",
      "views": 2.3865272581188333e-05
    },
    {
      "date": "2021-07-05",
      "views": 2.643100780111195e-05
    },
    {
      "date": "2020-11-07",
      "views": 3.4980323567993004e-05
    },
    {
      "date": "2019-05-26",
      "views": 1.3367568017785035e-05
    },
    {
      "date": "2019-06-16",
      "views": 1.699780515840892e-05
    },
    {
      "date": "2021-09-11",
      "views": 2.85301169620675e-05
    },
    {
      "date": "2019-04-28",
      "views": 2.564672491322858e-05
    },
    {
      "date": "2019-07-30",
      "views": 1.9374940210145445e-05
    },
    {
      "date": "2019-06-20",
      "views": 1.8955549237039144e-05
    },
    {
      "date": "2021-05-22",
      "views": 1.1114210740995544e-05
    },
    {
      "date": "2019-10-18",
      "views": 1.5017720910674597e-05
    },
    {
      "date": "2019-10-17",
      "views": 1.9579220790521916e-05
    },
    {
      "date": "2021-08-16",
      "views": 1.1884883023038846e-05
    },
    {
      "date": "2019-06-25",
      "views": 1.1931778861183298e-05
    },
    {
      "date": "2020-10-23",
      "views": 2.17842692352231e-05
    },
    {
      "date": "2021-08-09",
      "views": 1.9972138866281536e-05
    },
    {
      "date": "2020-07-02",
      "views": 2.2847546887450127e-05
    },
    {
      "date": "2020-07-21",
      "views": 1.9586106399564406e-05
    },
    {
      "date": "2019-05-19",
      "views": 2.481414207585187e-05
    },
    {
      "date": "2020-09-09",
      "views": 1.0401746661299366e-05
    },
    {
      "date": "2019-12-26",
      "views": 5.095243776346139e-05
    },
    {
      "date": "2019-03-31",
      "views": 2.3570022787926578e-05
    },
    {
      "date": "2019-07-28",
      "views": 1.9141068478368797e-05
    },
    {
      "date": "2019-09-02",
      "views": 1.8373619681821402e-05
    },
    {
      "date": "2020-03-16",
      "views": 2.2849685880290495e-05
    },
    {
      "date": "2020-07-13",
      "views": 1.5048332507955096e-05
    },
    {
      "date": "2020-03-14",
      "views": 2.8544013771388797e-05
    },
    {
      "date": "2019-03-15",
      "views": 2.8484597501681687e-05
    },
    {
      "date": "2019-07-23",
      "views": 2.5681992057506036e-05
    },
    {
      "date": "2021-09-03",
      "views": 2.4712743773565367e-05
    },
    {
      "date": "2021-07-04",
      "views": 2.296184888807247e-05
    },
    {
      "date": "2021-06-29",
      "views": 1.7856960643258744e-05
    },
    {
      "date": "2019-04-01",
      "views": 2.259789510878832e-05
    },
    {
      "date": "2020-09-20",
      "views": 2.1437605848178874e-05
    },
    {
      "date": "2021-06-04",
      "views": 1.4758270875574153e-05
    },
    {
      "date": "2019-08-21",
      "views": 3.1054318972574066e-05
    },
    {
      "date": "2020-07-12",
      "views": 1.9239747779733107e-05
    },
    {
      "date": "2019-12-19",
      "views": 2.170513097237781e-05
    },
    {
      "date": "2019-09-01",
      "views": 2.4325211865838348e-05
    },
    {
      "date": "2020-06-23",
      "views": 2.5549440722742578e-05
    },
    {
      "date": "2020-10-31",
      "views": 1.4364749725017649e-05
    },
    {
      "date": "2020-10-09",
      "views": 1.8757834154264427e-05
    },
    {
      "date": "2020-07-23",
      "views": 1.9374262970746156e-05
    },
    {
      "date": "2020-07-26",
      "views": 2.1047338973240648e-05
    },
    {
      "date": "2021-08-04",
      "views": 1.0234458654705995e-05
    },
    {
      "date": "2019-08-23",
      "views": 1.1741989353929653e-05
    },
    {
      "date": "2020-08-27",
      "views": 1.8213991988645676e-05
    },
    {
      "date": "2021-07-07",
      "views": 1.1850899878330761e-05
    },
    {
      "date": "2020-07-01",
      "views": 2.025987632792636e-05
    },
    {
      "date": "2020-08-21",
      "views": 2.3249629822300172e-05
    },
    {
      "date": "2021-07-15",
      "views": 1.622937516905599e-05
    },
    {
      "date": "2021-06-22",
      "views": 2.1838935424694498e-05
    },
    {
      "date": "2019-07-08",
      "views": 1.7923642525358508e-05
    },
    {
      "date": "2019-06-06",
      "views": 2.941779147452115e-05
    },
    {
      "date": "2020-10-30",
      "views": 1.3979464167138473e-05
    },
    {
      "date": "2019-10-26",
      "views": 1.897602650137644e-05
    },
    {
      "date": "2019-08-14",
      "views": 2.3443679028888783e-05
    },
    {
      "date": "2019-06-13",
      "views": 2.676307320369598e-05
    },
    {
      "date": "2020-06-28",
      "views": 1.377261865684832e-05
    },
    {
      "date": "2020-08-17",
      "views": 1.640361645064015e-05
    },
    {
      "date": "2019-08-06",
      "views": 1.8829580194509565e-05
    },
    {
      "date": "2020-08-29",
      "views": 2.1099598544971686e-05
    },
    {
      "date": "2019-08-07",
      "views": 1.4641268945469259e-05
    },
    {
      "date": "2020-08-10",
      "views": 1.8821226579336177e-05
    },
    {
      "date": "2019-08-11",
      "views": 2.060920819422118e-05
    },
    {
      "date": "2019-04-06",
      "views": 5.022419848603242e-05
    },
    {
      "date": "2020-08-28",
      "views": 2.395786797523602e-05
    },
    {
      "date": "2019-08-05",
      "views": 2.374541746422687e-05
    },
    {
      "date": "2021-06-28",
      "views": 1.619298584625084e-05
    },
    {
      "date": "2020-06-17",
      "views": 1.5210994038460413e-05
    },
    {
      "date": "2021-08-12",
      "views": 6.357691344257542e-06
    },
    {
      "date": "2021-09-25",
      "views": 2.9074521633261254e-05
    },
    {
      "date": "2019-06-12",
      "views": 2.015912980463681e-05
    },
    {
      "date": "2019-04-27",
      "views": 2.9689589404854367e-05
    },
    {
      "date": "2019-06-10",
      "views": 1.3389817764580224e-05
    },
    {
      "date": "2019-08-15",
      "views": 1.0262910099473256e-05
    },
    {
      "date": "2020-09-18",
      "views": 9.700356003065313e-06
    },
    {
      "date": "2019-10-19",
      "views": 1.725055367642473e-05
    },
    {
      "date": "2019-11-01",
      "views": 3.3443573260005205e-05
    },
    {
      "date": "2021-06-26",
      "views": 1.7258065158488776e-05
    },
    {
      "date": "2019-10-25",
      "views": 3.2274430775864405e-05
    },
    {
      "date": "2020-07-07",
      "views": 4.022260337927329e-05
    },
    {
      "date": "2019-05-23",
      "views": 2.1218722592483318e-05
    },
    {
      "date": "2020-07-22",
      "views": 3.0433384629023657e-05
    },
    {
      "date": "2020-07-30",
      "views": 2.037927183503115e-05
    },
    {
      "date": "2019-07-10",
      "views": 1.8102051608949137e-05
    },
    {
      "date": "2019-07-29",
      "views": 1.9893841488357752e-05
    },
    {
      "date": "2020-12-29",
      "views": 1.3243629814059438e-05
    },
    {
      "date": "2020-07-06",
      "views": 2.9512454255695902e-05
    },
    {
      "date": "2020-07-20",
      "views": 2.8435381887178745e-05
    },
    {
      "date": "2019-12-29",
      "views": 2.3301268959694288e-05
    },
    {
      "date": "2019-07-31",
      "views": 1.9442644199611147e-05
    },
    {
      "date": "2020-06-22",
      "views": 1.527419081792019e-05
    },
    {
      "date": "2020-06-13",
      "views": 2.3956753831671394e-05
    },
    {
      "date": "2019-07-09",
      "views": 1.546798385142486e-05
    },
    {
      "date": "2020-09-22",
      "views": 1.3857945399695125e-05
    },
    {
      "date": "2020-10-10",
      "views": 1.01076336639793e-05
    },
    {
      "date": "2021-06-25",
      "views": 1.3054009182902096e-05
    },
    {
      "date": "2019-03-08",
      "views": 3.742700225407139e-05
    },
    {
      "date": "2019-08-08",
      "views": 2.6880894596172162e-05
    },
    {
      "date": "2019-08-22",
      "views": 2.437463037155917e-05
    },
    {
      "date": "2021-04-29",
      "views": 1.6845926037400203e-05
    },
    {
      "date": "2021-07-16",
      "views": 2.2727546187053052e-05
    },
    {
      "date": "2021-07-13",
      "views": 1.0704016548409584e-05
    },
    {
      "date": "2020-09-03",
      "views": 7.978108071451936e-06
    },
    {
      "date": "2020-06-21",
      "views": 1.313853268866933e-05
    },
    {
      "date": "2019-07-03",
      "views": 2.621854120036761e-05
    },
    {
      "date": "2019-03-16",
      "views": 3.150414804615941e-05
    },
    {
      "date": "2020-08-19",
      "views": 4.22096765683533e-05
    },
    {
      "date": "2020-09-10",
      "views": 1.9737231655887944e-05
    },
    {
      "date": "2020-09-07",
      "views": 1.4096388938888902e-05
    },
    {
      "date": "2019-08-01",
      "views": 1.69137813490432e-05
    },
    {
      "date": "2019-08-19",
      "views": 1.2850084489305518e-05
    },
    {
      "date": "2019-09-14",
      "views": 1.5032225333057742e-05
    },
    {
      "date": "2021-08-03",
      "views": 2.2495877961185348e-05
    },
    {
      "date": "2020-09-25",
      "views": 1.8236239541516623e-05
    },
    {
      "date": "2020-09-02",
      "views": 1.3025489699205919e-05
    },
    {
      "date": "2020-07-24",
      "views": 1.9379143906938766e-05
    },
    {
      "date": "2019-06-21",
      "views": 3.419556825435424e-05
    },
    {
      "date": "2019-06-01",
      "views": 1.825662886783798e-05
    },
    {
      "date": "2021-07-20",
      "views": 2.5335986855690018e-05
    },
    {
      "date": "2020-08-22",
      "views": 2.4404144110777587e-05
    },
    {
      "date": "2019-04-26",
      "views": 2.1648119439890988e-05
    },
    {
      "date": "2020-07-28",
      "views": 1.4970630345195517e-05
    },
    {
      "date": "2021-08-11",
      "views": 2.8058110898407958e-05
    },
    {
      "date": "2021-08-13",
      "views": 2.177081225619892e-05
    },
    {
      "date": "2020-10-02",
      "views": 1.9945443346141435e-05
    },
    {
      "date": "2021-07-11",
      "views": 2.8169505303244726e-05
    },
    {
      "date": "2020-08-07",
      "views": 1.20299304670019e-05
    },
    {
      "date": "2021-09-04",
      "views": 2.4670270092466522e-05
    },
    {
      "date": "2019-04-24",
      "views": 1.6264412883738492e-05
    },
    {
      "date": "2021-07-14",
      "views": 1.9799601632015164e-05
    },
    {
      "date": "2020-08-08",
      "views": 3.062391568037686e-05
    },
    {
      "date": "2021-08-08",
      "views": 2.768911666683448e-05
    },
    {
      "date": "2021-06-30",
      "views": 2.520017560543422e-05
    },
    {
      "date": "2020-07-04",
      "views": 3.687397213802665e-05
    },
    {
      "date": "2019-03-23",
      "views": 2.19441545648718e-05
    },
    {
      "date": "2020-09-11",
      "views": 1.2299941452278686e-05
    },
    {
      "date": "2021-08-05",
      "views": 1.7734202309246487e-05
    },
    {
      "date": "2019-06-15",
      "views": 1.395432622170126e-05
    },
    {
      "date": "2020-06-18",
      "views": 2.55916858705865e-05
    },
    {
      "date": "2019-05-10",
      "views": 2.6250320671530932e-05
    },
    {
      "date": "2019-09-06",
      "views": 1.1574208034815218e-05
    },
    {
      "date": "2019-06-07",
      "views": 1.073283819173142e-05
    },
    {
      "date": "2021-07-28",
      "views": 1.5739624636185135e-05
    },
    {
      "date": "2020-08-12",
      "views": 1.9511270546064715e-05
    },
    {
      "date": "2019-01-01",
      "views": 2.1453702909122115e-05
    },
    {
      "date": "2020-01-01",
      "views": 2.013791595584618e-05
    },
    {
      "date": "2019-07-07",
      "views": 1.9625441899533437e-05
    },
    {
      "date": "2020-08-13",
      "views": 2.6550737761157946e-05
    },
    {
      "date": "2019-07-04",
      "views": 1.5045697887857575e-05
    },
    {
      "date": "2020-08-16",
      "views": 2.7908404616050125e-05
    },
    {
      "date": "2021-07-01",
      "views": 3.276247988383735e-05
    },
    {
      "date": "2019-07-21",
      "views": 2.2257601625590482e-05
    },
    {
      "date": "2020-08-03",
      "views": 2.0746773185210593e-05
    },
    {
      "date": "2020-09-12",
      "views": 1.4321163815887119e-05
    },
    {
      "date": "2019-08-30",
      "views": 2.2469227690514474e-05
    },
    {
      "date": "2019-06-30",
      "views": 2.8786542553052288e-05
    },
    {
      "date": "2019-08-03",
      "views": 2.030456852791878e-05
    },
    {
      "date": "2019-04-20",
      "views": 2.215283895146704e-05
    },
    {
      "date": "2020-06-30",
      "views": 1.9810049921325803e-05
    },
    {
      "date": "2021-07-10",
      "views": 1.1355877589317526e-05
    },
    {
      "date": "2021-07-08",
      "views": 2.1343208124292172e-05
    },
    {
      "date": "2020-09-06",
      "views": 1.1390377864395273e-05
    },
    {
      "date": "2019-07-17",
      "views": 6.610203341106183e-05
    },
    {
      "date": "2019-08-04",
      "views": 2.6053911746716275e-05
    },
    {
      "date": "2019-06-26",
      "views": 2.18472210977329e-05
    },
    {
      "date": "2020-07-03",
      "views": 2.1923926896858156e-05
    },
    {
      "date": "2019-08-09",
      "views": 1.649949470297472e-05
    },
    {
      "date": "2021-07-09",
      "views": 1.5232777613910018e-05
    },
    {
      "date": "2019-07-24",
      "views": 1.9008877145627007e-05
    },
    {
      "date": "2020-08-20",
      "views": 3.8508384844240715e-05
    },
    {
      "date": "2021-08-02",
      "views": 3.0088092702721795e-05
    },
    {
      "date": "2020-08-11",
      "views": 2.1230821491252903e-05
    },
    {
      "date": "2021-07-21",
      "views": 3.350679543585897e-05
    },
    {
      "date": "2020-06-26",
      "views": 2.9687112675951806e-05
    },
    {
      "date": "2019-07-11",
      "views": 8.318798543655668e-06
    },
    {
      "date": "2019-06-28",
      "views": 1.3515887926257316e-05
    },
    {
      "date": "2019-08-31",
      "views": 1.953345732427911e-05
    },
    {
      "date": "2019-05-24",
      "views": 1.901267194585191e-05
    },
    {
      "date": "2020-09-05",
      "views": 1.5595960646192635e-05
    },
    {
      "date": "2020-06-24",
      "views": 3.544235006409158e-05
    },
    {
      "date": "2021-07-03",
      "views": 2.8061628949498888e-05
    },
    {
      "date": "2020-07-29",
      "views": 2.3661984377522786e-05
    },
    {
      "date": "2021-05-01",
      "views": 2.3568091161376613e-05
    },
    {
      "date": "2019-06-27",
      "views": 1.5597744566135736e-05
    },
    {
      "date": "2021-07-02",
      "views": 1.238195866076735e-05
    },
    {
      "date": "2021-07-22",
      "views": 2.0703505103414008e-05
    },
    {
      "date": "2020-08-04",
      "views": 2.905118819359712e-05
    },
    {
      "date": "2020-07-31",
      "views": 3.739188711101651e-05
    },
    {
      "date": "2019-07-02",
      "views": 1.0844678448506078e-05
    },
    {
      "date": "2019-07-22",
      "views": 2.5820444628056494e-05
    },
    {
      "date": "2019-12-20",
      "views": 2.7514353320982444e-05
    },
    {
      "date": "2021-08-14",
      "views": 1.515951600718561e-05
    },
    {
      "date": "2020-07-15",
      "views": 2.8636966314336523e-05
    },
    {
      "date": "2020-07-14",
      "views": 1.9715727376554902e-05
    },
    {
      "date": "2021-07-12",
      "views": 1.5110097666176734e-05
    },
    {
      "date": "2020-09-19",
      "views": 7.97774740324322e-06
    },
    {
      "date": "2019-12-28",
      "views": 3.3814528779839487e-05
    },
    {
      "date": "2019-03-30",
      "views": 1.8841073036791592e-05
    },
    {
      "date": "2019-07-25",
      "views": 1.2384258781471497e-05
    },
    {
      "date": "2019-07-01",
      "views": 2.728516682833128e-06
    },
    {
      "date": "2019-08-18",
      "views": 2.3959301133807372e-05
    },
    {
      "date": "2021-08-07",
      "views": 2.0800543587539087e-05
    },
    {
      "date": "2020-09-04",
      "views": 1.0073714405159757e-05
    },
    {
      "date": "2019-05-11",
      "views": 2.3065597277234385e-05
    },
    {
      "date": "2021-07-26",
      "views": 2.1724519514728546e-05
    },
    {
      "date": "2020-06-29",
      "views": 2.2107325538658805e-05
    },
    {
      "date": "2020-07-27",
      "views": 1.719378854549807e-05
    },
    {
      "date": "2021-07-29",
      "views": 1.504736500119695e-05
    },
    {
      "date": "2019-04-19",
      "views": 2.918204010373581e-05
    },
    {
      "date": "2019-05-17",
      "views": 1.0688569524988095e-05
    },
    {
      "date": "2019-05-31",
      "views": 1.4495589716828654e-05
    },
    {
      "date": "2021-07-17",
      "views": 0.00012746769490607225
    },
    {
      "date": "2020-09-01",
      "views": 1.7352166217734983e-05
    },
    {
      "date": "2021-07-27",
      "views": 1.9684910204001284e-05
    },
    {
      "date": "2021-08-06",
      "views": 2.3569144939150014e-05
    },
    {
      "date": "2021-08-01",
      "views": 1.575007776600897e-05
    },
    {
      "date": "2019-07-14",
      "views": 2.5237866895489993e-05
    },
    {
      "date": "2019-07-18",
      "views": 4.157963817398861e-05
    },
    {
      "date": "2019-06-08",
      "views": 1.1715836295921196e-05
    },
    {
      "date": "2019-06-29",
      "views": 2.8321431251849744e-05
    },
    {
      "date": "2019-06-22",
      "views": 2.3045316581647525e-05
    },
    {
      "date": "2020-06-27",
      "views": 1.273843880524767e-05
    },
    {
      "date": "2019-07-05",
      "views": 1.7617782214848853e-05
    },
    {
      "date": "2019-07-13",
      "views": 2.0954366628075707e-05
    },
    {
      "date": "2019-07-16",
      "views": 2.3291499972598236e-05
    },
    {
      "date": "2021-07-25",
      "views": 1.205455086082887e-05
    },
    {
      "date": "2019-07-26",
      "views": 1.6908814987973607e-05
    },
    {
      "date": "2020-08-15",
      "views": 2.8824772833337907e-05
    },
    {
      "date": "2019-12-30",
      "views": 2.1315728571602576e-05
    },
    {
      "date": "2019-05-25",
      "views": 2.521133400731633e-05
    },
    {
      "date": "2019-08-16",
      "views": 1.7875312817974314e-05
    },
    {
      "date": "2019-07-12",
      "views": 2.1815897098776565e-05
    },
    {
      "date": "2020-08-01",
      "views": 2.5603787084596336e-05
    },
    {
      "date": "2019-07-27",
      "views": 2.1460724192137862e-05
    },
    {
      "date": "2019-07-20",
      "views": 1.9528844102739745e-05
    },
    {
      "date": "2021-07-30",
      "views": 1.3870202643660623e-05
    },
    {
      "date": "2020-06-19",
      "views": 1.6321223438908982e-05
    },
    {
      "date": "2019-05-18",
      "views": 2.837083997782346e-05
    },
    {
      "date": "2020-07-11",
      "views": 2.567052932631471e-05
    },
    {
      "date": "2020-06-20",
      "views": 2.0198493480936228e-05
    },
    {
      "date": "2019-08-10",
      "views": 1.545358375631665e-05
    },
    {
      "date": "2019-07-19",
      "views": 2.5798684267102377e-05
    },
    {
      "date": "2019-07-15",
      "views": 2.0975324628107495e-05
    },
    {
      "date": "2019-12-27",
      "views": 6.050582872816748e-05
    },
    {
      "date": "2020-08-14",
      "views": 8.618993100496023e-06
    },
    {
      "date": "2019-07-06",
      "views": 1.78903678259625e-05
    },
    {
      "date": "2020-08-31",
      "views": 1.2825738121228877e-05
    },
    {
      "date": "2021-07-31",
      "views": 1.4458075196449097e-05
    },
    {
      "date": "2019-04-25",
      "views": 2.58600508490263e-05
    },
    {
      "date": "2019-08-17",
      "views": 1.6008825228744283e-05
    },
    {
      "date": "2021-07-23",
      "views": 2.0894915292013406e-05
    },
    {
      "date": "2020-07-09",
      "views": 3.348350686160764e-05
    },
    {
      "date": "2020-12-31",
      "views": 7.648908959625999e-06
    },
    {
      "date": "2020-07-10",
      "views": 2.6000871029179476e-05
    },
    {
      "date": "2021-07-24",
      "views": 2.0910721673813653e-05
    },
    {
      "date": "2019-12-31",
      "views": 1.4456141872576338e-05
    },
    {
      "date": "2020-07-08",
      "views": 3.167107129158148e-05
    }
  ]
}