{
  "changepoint": "2021-09-01",
  "country": {
    "code": "ARE",
    "group": "ar",
    "name": "United Arab Emirates"
  },
  "topics": [
    {
      "diff": 13183.0,
      "topic": "Science"
    },
    {
      "diff": 9821.0,
      "topic": "Components"
    },
    {
      "diff": 9780.0,
      "topic": "Islamic texts"
    },
    {
      "diff": 9777.0,
      "topic": "Medieval arabic texts"
    },
    {
      "diff": 9467.0,
      "topic": "7th-century books"
    },
    {
      "diff": 8956.0,
      "topic": "Branches"
    },
    {
      "diff": 7981.0,
      "topic": "Philosophy"
    },
    {
      "diff": 7949.0,
      "topic": "Biology"
    },
    {
      "diff": 7424.0,
      "topic": "Culture"
    },
    {
      "diff": 7205.0,
      "topic": "Language"
    },
    {
      "diff": 6842.0,
      "topic": "Technology"
    },
    {
      "diff": 6743.0,
      "topic": "Subfields"
    },
    {
      "diff": 6432.0,
      "topic": "Humanities"
    },
    {
      "diff": 6033.0,
      "topic": "Religion"
    },
    {
      "diff": 5982.0,
      "topic": "Natural sciences"
    },
    {
      "diff": 5395.0,
      "topic": "Politics"
    },
    {
      "diff": 5017.0,
      "topic": "Matter"
    },
    {
      "diff": 4758.0,
      "topic": "History"
    },
    {
      "diff": 4597.0,
      "topic": "Topic"
    },
    {
      "diff": 4404.0,
      "topic": "Physics"
    }
  ]
}